.gitignore
.pre-commit-config.yaml
AUTHORS
CHANGELOG.md
LICENSE
MANIFEST.in
README.rst
__init__.py
pyproject.toml
pytest.ini
setup.cfg
setup.py
.github/workflows/flake8.yml
.github/workflows/publish.yml
.github/workflows/test.yml
ce_ui/__init__.py
ce_ui/apps.py
ce_ui/context_processors.py
ce_ui/serializers.py
ce_ui/signals.py
ce_ui/urls.py
ce_ui/utils.py
ce_ui/views.py
ce_ui.egg-info/PKG-INFO
ce_ui.egg-info/SOURCES.txt
ce_ui.egg-info/dependency_links.txt
ce_ui.egg-info/entry_points.txt
ce_ui.egg-info/requires.txt
ce_ui.egg-info/top_level.txt
ce_ui/management/commands/import_terms.py
ce_ui/static/images/README.md
ce_ui/static/images/ce_logo.svg
ce_ui/static/images/erc_logo.png
ce_ui/static/images/logo_livmats_small.jpg
ce_ui/static/images/pitt_logo.png
ce_ui/static/images/screenshot_contact_mechanics.png
ce_ui/static/images/screenshot_psd.png
ce_ui/static/images/thumbnail_unavailable.png
ce_ui/static/images/uni_freiburg_logo.png
ce_ui/static/images/cc/cc0-1.0.svg
ce_ui/static/images/cc/ccby-4.0.svg
ce_ui/static/images/cc/ccbysa-4.0.svg
ce_ui/static/images/favicons/favicon.png
ce_ui/static/other/CHANGELOG.md
ce_ui/static/other/TermsConditions-2.0.md
ce_ui/static/other/TermsConditions.md
ce_ui/static/other/TermsConditionsSupplement.md
ce_ui/static/vendor/openseadragon/FileSaver.min.js
ce_ui/static/vendor/openseadragon/FileSaver.min.js.map
ce_ui/static/vendor/openseadragon/openseadragon-scalebar.js
ce_ui/static/vendor/openseadragon/openseadragon.min.js
ce_ui/static/vendor/openseadragon/openseadragon.min.js.map
ce_ui/templates/403.html
ce_ui/templates/403_csrf.html
ce_ui/templates/404.html
ce_ui/templates/500.html
ce_ui/templates/base.html
ce_ui/templates/account/account_inactive.html
ce_ui/templates/account/base.html
ce_ui/templates/account/email.html
ce_ui/templates/account/email_confirm.html
ce_ui/templates/account/login.html
ce_ui/templates/account/logout.html
ce_ui/templates/account/password_change.html
ce_ui/templates/account/password_reset.html
ce_ui/templates/account/password_reset_done.html
ce_ui/templates/account/password_reset_from_key.html
ce_ui/templates/account/password_reset_from_key_done.html
