Metadata-Version: 2.1
Name: ce-ui
Version: 1.7.0
Summary: The user-facing interface of contact.engineering.
Author-email: Michael Röttger <info@michael-roettger.de>, Lars Pastewka <lars.pastewka@imtek.uni-freiburg.de>
License: MIT License
Project-URL: homepage, https://contact.engineering
Project-URL: repository, https://github.com/ContactEngineering/ce-ui
Classifier: Development Status :: 5 - Production/Stable
Classifier: Environment :: Web Environment
Classifier: Framework :: Django
Classifier: Framework :: Django :: 3.2
Classifier: Framework :: Celery
Classifier: Intended Audience :: Developers
Classifier: License :: OSI Approved :: MIT License
Classifier: Operating System :: POSIX
Classifier: Programming Language :: Python
Classifier: Programming Language :: Python :: 3
Classifier: Programming Language :: Python :: 3 :: Only
Classifier: Programming Language :: Python :: 3.8
Classifier: Programming Language :: Python :: 3.9
Classifier: Topic :: Internet :: WWW/HTTP
Classifier: Topic :: Internet :: WWW/HTTP :: Dynamic Content
Requires-Python: >=3.8.0
License-File: LICENSE
License-File: AUTHORS
Requires-Dist: django
Requires-Dist: django-termsandconditions>=2.0.8
Provides-Extra: dev
